koo_api/__init__.py
koo_api/client.py
koo_api/constants.py
koo_api-0.0.3.dist-info/entry_points.txt
koo_api-0.0.3.dist-info/LICENSE
koo_api-0.0.3.dist-info/WHEEL
koo_api-0.0.3.dist-info/METADATA
koo_api-0.0.3.dist-info/RECORD
